Inputbetter/__init__.py
Inputbetter/functions.py
Inputbetter-0.5.4.dist-info/METADATA
Inputbetter-0.5.4.dist-info/WHEEL
Inputbetter-0.5.4.dist-info/top_level.txt
Inputbetter-0.5.4.dist-info/RECORD
