Metadata-Version: 2.1
Name: Inputbetter
Version: 0.5.4
Summary: A library to make entering data into lists easier!
Author: Sankie
License: MIT
